MANIFEST.in
README.md
setup.cfg
setup.py
storm/__init__.py
storm/__main__.py
storm/defaults.py
storm/kommandr.py
storm/utils.py
storm/web.py
storm/parsers/__init__.py
storm/parsers/ssh_config_parser.py
storm/parsers/ssh_uri_parser.py
storm/parsers/storm_config_parser.py
storm/static/css/themes/black/style.css
storm/static/css/themes/black/img/delete.png
storm/static/css/themes/black/img/edit.png
storm/static/css/themes/modern/style.css
storm/static/css/themes/storm/normalize.min.css
storm/static/css/themes/storm/style.css
storm/static/css/themes/storm/img/delete.png
storm/static/css/themes/storm/img/edit.png
storm/static/css/themes/storm/img/info.png
storm/static/css/themes/storm/img/logo.png
storm/static/js/main.js
storm/static/js/core/angular.min.js
storm/templates/index.html
stormssh.egg-info/PKG-INFO
stormssh.egg-info/SOURCES.txt
stormssh.egg-info/dependency_links.txt
stormssh.egg-info/entry_points.txt
stormssh.egg-info/requires.txt
stormssh.egg-info/top_level.txt