Metadata-Version: 1.1
Name: stormssh
Version: 0.7.0
Summary: Management commands to ssh config files.
Home-page: http://github.com/emre/storm
Author: Emre Yilmaz
Author-email: mail@emreyilmaz.me
License: MIT
Platform: UNKNOWN
Classifier: Development Status :: 5 - Production/Stable
Classifier: Intended Audience :: Developers
Classifier: Intended Audience :: System Administrators
Classifier: Programming Language :: Python
Classifier: Programming Language :: Python :: 2
Classifier: Programming Language :: Python :: 2.7
Classifier: Programming Language :: Python :: 3
Classifier: Programming Language :: Python :: 3.2
Classifier: Programming Language :: Python :: 3.3
Classifier: Programming Language :: Python :: 3.4
Classifier: License :: OSI Approved :: MIT License
Classifier: Topic :: System :: Systems Administration
